.installed.cfg
.mr.developer.cfg
.travis.yml
MANIFEST.in
README.rst
bootstrap.py
buildout.cfg
pre-commit-check.sh
setup.cfg
setup.py
buildout.d/base.cfg
buildout.d/development.cfg
buildout.d/travis.cfg
buildout.d/versions.cfg
docs/HISTORY.rst
docs/LICENSE.rst
docs/images/correct_answer_field.png
docs/images/quiz_in_overlay.png
docs/images/quizzes_view.png
docs/images/result_on_thank_you_page.png
src/osha/__init__.py
src/osha/__init__.pyc
src/osha.quizzes.egg-info/PKG-INFO
src/osha.quizzes.egg-info/SOURCES.txt
src/osha.quizzes.egg-info/dependency_links.txt
src/osha.quizzes.egg-info/entry_points.txt
src/osha.quizzes.egg-info/namespace_packages.txt
src/osha.quizzes.egg-info/not-zip-safe
src/osha.quizzes.egg-info/requires.txt
src/osha.quizzes.egg-info/top_level.txt
src/osha/quizzes/.DS_Store
src/osha/quizzes/__init__.py
src/osha/quizzes/__init__.pyc
src/osha/quizzes/config.py
src/osha/quizzes/config.pyc
src/osha/quizzes/configure.zcml
src/osha/quizzes/extender.py
src/osha/quizzes/extender.pyc
src/osha/quizzes/interfaces.py
src/osha/quizzes/interfaces.pyc
src/osha/quizzes/browser/__init__.py
src/osha/quizzes/browser/__init__.pyc
src/osha/quizzes/browser/configure.zcml
src/osha/quizzes/browser/quizzes.pt
src/osha/quizzes/browser/quizzes.py
src/osha/quizzes/browser/quizzes.pyc
src/osha/quizzes/browser/static/.gitignore
src/osha/quizzes/browser/static/correct_answers_icon.png
src/osha/quizzes/browser/static/quizzes.js
src/osha/quizzes/content/__init__.py
src/osha/quizzes/content/__init__.pyc
src/osha/quizzes/content/configure.zcml
src/osha/quizzes/content/pfgcorrectanswersadapter.py
src/osha/quizzes/content/pfgcorrectanswersadapter.pyc
src/osha/quizzes/profiles/.DS_Store
src/osha/quizzes/profiles/default/factorytool.xml
src/osha/quizzes/profiles/default/jsregistry.xml
src/osha/quizzes/profiles/default/metadata.xml
src/osha/quizzes/profiles/default/types.xml
src/osha/quizzes/profiles/default/types/FieldsetFolder.xml
src/osha/quizzes/profiles/default/types/Folder.xml
src/osha/quizzes/profiles/default/types/FormFolder.xml
src/osha/quizzes/profiles/default/types/PFGCorrectAnswersAdapter.xml
src/osha/quizzes/tests/__init__.py
src/osha/quizzes/tests/__init__.pyc
src/osha/quizzes/tests/base.py
src/osha/quizzes/tests/base.pyc
src/osha/quizzes/tests/test_content.py
src/osha/quizzes/tests/test_content.pyc
