Metadata-Version: 1.0
Name: osha.quizzes
Version: 0.1
Summary: A simple add-on to build quizzes with PloneFormGen.
Home-page: https://github.com/syslabcom/osha.quizzes
Author: Syslab.com GmbH
Author-email: UNKNOWN
License: BSD
Keywords: Plone Python
Platform: UNKNOWN
Classifier: Framework :: Plone
Classifier: Programming Language :: Python
